src/__init__.py
sshpass_wrapper-0.0.3.data/scripts/spw
sshpass_wrapper-0.0.3.dist-info/LICENSE
sshpass_wrapper-0.0.3.dist-info/METADATA
sshpass_wrapper-0.0.3.dist-info/WHEEL
sshpass_wrapper-0.0.3.dist-info/top_level.txt
sshpass_wrapper-0.0.3.dist-info/RECORD
