Metadata-Version: 2.1
Name: sshpass-wrapper
Version: 0.0.3
Summary: A wrapper for sshpass
Home-page: https://github.com/ileler/spw
Author: ileler
Author-email: kerwin612@qq.com
License: UNKNOWN
Platform: UNKNOWN
Classifier: Programming Language :: Python :: 3
Classifier: License :: OSI Approved :: MIT License
Classifier: Operating System :: OS Independent
